{"name":"Accompagnement psycho-émotionnel","tagline":"","body":"### Accompagnement psycho-émotionnel à Carbonne\r\nchâteau la terrasse<br/>\r\n1 route de Cazéres<br/>\r\n06 67 50 25 97\r\n\r\n### Aide ponctuelle ou suivie\r\nsoin, conseil, travail sur les plans :\r\n- physique, \r\n- émotionnel, \r\n- mental\r\n\r\nénergétique chinoise\r\n\r\n### Techniques\r\n- nœuds émotionnels\r\n- rêve éveillé\r\n- ESR\r\n- la trame\r\n\r\n","google":"","note":"Don't delete this file! It's used internally to help with page regeneration."}